camina/__init__.py
camina/base.py
camina/clock.py
camina/convert.py
camina/label.py
camina/mapping.py
camina/modify.py
camina/rules.py
camina/sequence.py
camina-0.1.16.dist-info/LICENSE
camina-0.1.16.dist-info/WHEEL
camina-0.1.16.dist-info/METADATA
camina-0.1.16.dist-info/RECORD
