Metadata-Version: 2.1
Name: camina
Version: 0.1.16
Summary: Your Python project companion
Home-page: https://github.com/WithPrecedent/camina
License: Apache-2.0
Author: corey rayburn yung
Author-email: coreyrayburnyung@gmail.com
Requires-Python: >=3.9,<4.0
Classifier: License :: OSI Approved :: Apache Software License
Classifier: Programming Language :: Python :: 3
Classifier: Programming Language :: Python :: 3.9
Classifier: Programming Language :: Python :: 3.10
Requires-Dist: miller (>=0.1.7,<0.2.0)
Project-URL: Repository, https://github.com/WithPrecedent/camina
